LICENSE
MANIFEST.in
README.md
setup.py
f311/__init__.py
f311/collaboration.py
f311/hapi.py
f311/pathfinder.py
f311/util.py
f311.egg-info/PKG-INFO
f311.egg-info/SOURCES.txt
f311.egg-info/dependency_links.txt
f311.egg-info/requires.txt
f311.egg-info/top_level.txt
f311/explorer/__init__.py
f311/explorer/util.py
f311/explorer/gui/__init__.py
f311/explorer/gui/a_XExplorer.py
f311/explorer/gui/a_XFileMainWindow.py
f311/explorer/gui/a_XSelectDataFile.py
f311/explorer/gui/a_XText.py
f311/explorer/vis/__init__.py
f311/explorer/vis/basic.py
f311/explorer/vis/plotsp.py
f311/explorer/vis/visprint.py
f311/explorer/vis/visspectrum.py
f311/filetypes/__init__.py
f311/filetypes/datafile.py
f311/filetypes/filefits.py
f311/filetypes/filepy.py
f311/filetypes/filespectrum.py
f311/filetypes/filesqlitedb.py
f311/filetypes/spectrum.py
f311/scripts/cut-spectrum.py
f311/scripts/explorer.py
f311/scripts/plot-spectra.py
f311/scripts/programs.py