Metadata-Version: 2.1
Name: f311
Version: 24.9.2.1
Summary: Astronomy-related API, command-line tools, and windowed applications
Home-page: https://github.com/trevisanj/f311
Author: Julio Trevisan
Author-email: juliotrevisan@gmail.com
License: GNU GPLv3
Keywords: astronomy,fits,spectroscopy,spectral synthesis,photometry,honl-london,nist,hitran,multiplicity,line strength,kovacs,franck-condon
Platform: any
License-File: LICENSE
